Task-1/jtag_tap.v
//Tap is finite state machine
module jtag_tap(  
	input tck,
	input tms,
	input tdi,
	input trst,
	
	output reg tdo
);

parameter TEST_LOGIC_RESET = 0;
parameter RUN_TEST_IDLE = 1;
parameter SHIFT_IR = 2;
parameter UPDATE_IR = 3;
parameter SHIFT_DR = 4;
parameter UPDATE_DR = 5;

reg[2:0] state;

parameter IDCODE = 4'b0001;
parameter BYPASS = 4'b1111;

reg[3:0] ir;
reg[3:0] ir_shift;

reg[31:0] idcode;
reg[31:0] dr_shift;
reg bypass_bit;


initial begin 
	state = TEST_LOGIC_RESET;
	ir = 4'b0000;
	ir_shift = 4'b0000;
	idcode = 32'h81262776;
	dr_shift = 32'h81262776;
	bypass_bit = 1'b0;
	tdo = 1'b0;
	
end

always @(posedge tck or posedge trst) begin
	
	if(trst)
		state <= TEST_LOGIC_RESET;
		
	else begin
		case (state)
		// TMS CONTROLS NAVIGATION
			TEST_LOGIC_RESET:
				if(tms)    
					state <= TEST_LOGIC_RESET;
				else 
					state <= RUN_TEST_IDLE;
			
			RUN_TEST_IDLE:
				if(tms) 
					state <= SHIFT_IR;
				else 
					state <= RUN_TEST_IDLE;
					
			SHIFT_IR:
				if(tms)
					state <= UPDATE_IR;
				else
					state <= SHIFT_IR;
					
			UPDATE_IR:
				if(tms)
					state <= SHIFT_DR;
				else 
					state <= RUN_TEST_IDLE;
				
			SHIFT_DR:
				if(tms)
					state <= UPDATE_DR;
				else 
					state <= SHIFT_DR;
					
			UPDATE_DR:
				if(tms)
					state <= TEST_LOGIC_RESET;
				else
					state <= RUN_TEST_IDLE;
		endcase
	end
end


always @(posedge tck) begin

	if(state == SHIFT_IR)
		ir_shift <= {tdi, ir_shift[3:1]};
	
end

always @(posedge tck) begin
	
	if(state == UPDATE_IR) begin
		ir <= ir_shift;
		
		if (ir_shift == IDCODE)
			dr_shift <= idcode;
	end
		
end


always @(posedge tck) begin

	if( state == SHIFT_DR) begin
		case (ir)
			
			IDCODE:
			begin 
				dr_shift <= {tdi, dr_shift[31:1]};
				
			end
			
			BYPASS:
			begin
				tdo <= bypass_bit;
				bypass_bit <= tdi;
			end
			
			default:
				tdo <= 0;
			
		endcase
	end
end


always @(*) begin
	case(ir) 
		IDCODE:
			tdo = dr_shift[0];
			
		BYPASS:
			tdo = bypass_bit;
			
		default:
			tdo = 0;
		
	endcase
end

endmodule

Task-1/tb_jtag_tap.v
module tb_jtag;

reg tck;
reg tms;
reg tdi;
reg trst;

wire tdo;

jtag_tap dut(
	.tck(tck),
	.tms(tms),
	.tdi(tdi),
	.trst(trst),
	.tdo(tdo)
);

always #5 tck = ~tck;

task jtag_clk;  // perform ONE JTAG clock operation
begin
	@(posedge tck);
	#1;             // signals samples too early
end 
endtask

// What operations we want done by SHIFT_IR

task shift_ir;  
input [3:0] instruction; //4 bit instruction 
integer i;

begin

	tms = 0; jtag_clk(); 
	tms = 1; jtag_clk(); 
	
	
	for( i = 0; i < 4; i = i + 1) begin   //JTAG is serial send bit one by one
		
		tdi = instruction[i];
		
		if(i == 3)       //after final bit change state
			tms = 1;     // moves to update_ir
		else
			tms = 0;
			
		jtag_clk();
	end

	
	tms =1;
	jtag_clk();
	
end 
endtask


task shift_dr;  //instructions loaded now data reading
integer i;

begin

	tms = 1; jtag_clk();
	
	for(i = 0; i < 32; i = i + 1) begin
		
		tdi = 0;
		
		if( i == 31)
			tms = 1;
		else 
			tms = 0;
			
		jtag_clk();
		
		$display("Bit %d : TDO = %b", i, tdo);
	end
	
	
	tms = 0; jtag_clk();
	
end
endtask

initial begin 

	$dumpfile("jtag_tap.vcd");
	$dumpvars(0, tb_jtag);
	
	tck = 0;
	tms = 1;
	tdi = 0;
	trst = 1;
	
	#20;
	trst = 0;
	
	$display(" Shift IDCODE Ins");
	
	shift_ir(4'b0001);
	
	$display(" Read Data Message ");
	
	shift_dr();
	
	#50;
	$finish;

end
endmodule

Task-1/jtag_tap.vcd
$date
	Sun May 24 23:15:26 2026
$end
$version
	Icarus Verilog
$end
$timescale
	1s
$end
$scope module tb_jtag $end
$var wire 1 ! tdo $end
$var reg 1 " tck $end
$var reg 1 # tdi $end
$var reg 1 $ tms $end
$var reg 1 % trst $end
$scope module dut $end
$var wire 1 " tck $end
$var wire 1 # tdi $end
$var wire 1 $ tms $end
$var wire 1 % trst $end
$var reg 1 & bypass_bit $end
$var reg 32 ' dr_shift [31:0] $end
$var reg 32 ( idcode [31:0] $end
$var reg 4 ) ir [3:0] $end
$var reg 4 * ir_shift [3:0] $end
$var reg 3 + state [2:0] $end
$var reg 1 ! tdo $end
$upscope $end
$scope task jtag_clk $end
$upscope $end
$scope task shift_dr $end
$var integer 32 , i [31:0] $end
$upscope $end
$scope task shift_ir $end
$var reg 4 - instruction [3:0] $end
$var integer 32 . i [31:0] $end
$upscope $end
$upscope $end
$enddefinitions $end
#0
$dumpvars
bx .
bx -
bx ,
b0 +
b0 *
b0 )
b10000001001001100010011101110110 (
b10000001001001100010011101110110 '
0&
1%
1$
0#
0"
0!
$end
#5
1"
#10
0"
#15
1"
#20
0"
0$
b1 -
0%
#25
b1 +
1"
#26
1$
#30
0"
#35
b10 +
1"
#36
0$
1#
b0 .
#40
0"
#45
b1000 *
1"
#46
0#
b1 .
#50
0"
#55
b100 *
1"
#56
b10 .
#60
0"
#65
b10 *
1"
#66
1$
b11 .
#70
0"
#75
b1 *
b11 +
1"
#76
b100 .
#80
0"
#85
b1 )
b100 +
1"
#90
0"
#95
1!
b1000000100100110001001110111011 '
b101 +
1"
#96
0$
b0 ,
#100
0"
#105
b1 +
1"
#106
b1 ,
#110
0"
#115
1"
#116
b10 ,
#120
0"
#125
1"
#126
b11 ,
#130
0"
#135
1"
#136
b100 ,
#140
0"
#145
1"
#146
b101 ,
#150
0"
#155
1"
#156
b110 ,
#160
0"
#165
1"
#166
b111 ,
#170
0"
#175
1"
#176
b1000 ,
#180
0"
#185
1"
#186
b1001 ,
#190
0"
#195
1"
#196
b1010 ,
#200
0"
#205
1"
#206
b1011 ,
#210
0"
#215
1"
#216
b1100 ,
#220
0"
#225
1"
#226
b1101 ,
#230
0"
#235
1"
#236
b1110 ,
#240
0"
#245
1"
#246
b1111 ,
#250
0"
#255
1"
#256
b10000 ,
#260
0"
#265
1"
#266
b10001 ,
#270
0"
#275
1"
#276
b10010 ,
#280
0"
#285
1"
#286
b10011 ,
#290
0"
#295
1"
#296
b10100 ,
#300
0"
#305
1"
#306
b10101 ,
#310
0"
#315
1"
#316
b10110 ,
#320
0"
#325
1"
#326
b10111 ,
#330
0"
#335
1"
#336
b11000 ,
#340
0"
#345
1"
#346
b11001 ,
#350
0"
#355
1"
#356
b11010 ,
#360
0"
#365
1"
#366
b11011 ,
#370
0"
#375
1"
#376
b11100 ,
#380
0"
#385
1"
#386
b11101 ,
#390
0"
#395
1"
#396
b11110 ,
#400
0"
#405
1"
#406
1$
b11111 ,
#410
0"
#415
b10 +
1"
#416
0$
b100000 ,
#420
0"
#425
b0 *
1"
#430
0"
#435
1"
#440
0"
#445
1"
#450
0"
#455
1"
#460
0"
#465
1"
#470
0"
#475
1"
