Task-1/jtag_tap.v
//Tap is finite state machine
module jtag_tap(  
	input tck,
	input tms,
	input tdi,
	input trst,
	
	output reg tdo
);

parameter TEST_LOGIC_RESET = 4'h0;
parameter RUN_TEST_IDLE = 4'h1;

parameter SHIFT_IR = 4'h2;
parameter UPDATE_IR = 4'h3;
parameter SELECT_IR_SCAN = 4'h4; 
parameter CAPTURE_IR = 4'h5;
parameter EXIT1_IR = 4'h6;
parameter PAUSE_IR = 4'h7;
parameter EXIT2_IR = 4'h8;

parameter SHIFT_DR = 4'h9;
parameter UPDATE_DR = 4'hA;
parameter SELECT_DR_SCAN = 4'hB; 
parameter CAPTURE_DR = 4'hC;
parameter EXIT1_DR = 4'hD;
parameter PAUSE_DR = 4'hE;
parameter EXIT2_DR = 4'hF;

reg[3:0] state;

parameter IDCODE = 4'b0001;
parameter BYPASS = 4'b1111;

reg[3:0] ir;
reg[3:0] ir_shift;

reg[31:0] idcode;
reg[31:0] dr_shift;
reg bypass_bit;


initial begin 
	state = TEST_LOGIC_RESET;
	ir = 4'b0000;
	ir_shift = 4'b0000;
	idcode = 32'h81262776;
	dr_shift = 32'h00000000;
	bypass_bit = 1'b0;
	tdo = 1'b0;
	
end

always @(posedge tck or posedge trst) begin
	
	if(trst)
		state <= TEST_LOGIC_RESET;
		
	else begin
		case (state)
		// TMS CONTROLS NAVIGATION
			TEST_LOGIC_RESET:
				if(tms)    
					state <= TEST_LOGIC_RESET;
				else 
					state <= RUN_TEST_IDLE;
			
			RUN_TEST_IDLE:
				if(tms) 
					state <= SELECT_DR_SCAN;
				else 
					state <= RUN_TEST_IDLE;
					
			SHIFT_IR:
				if(tms)
					state <= EXIT1_IR;
				else
					state <= SHIFT_IR;
					
			UPDATE_IR:
				if(tms)
					state <= SELECT_DR_SCAN;
				else 
					state <= RUN_TEST_IDLE;
				
			SELECT_IR_SCAN:
				if(tms) 
					state <= TEST_LOGIC_RESET;
				else
					state <= CAPTURE_IR;
					
			CAPTURE_IR: 
				if(tms)
					state <= EXIT1_IR;
				else
					state <= SHIFT_IR;
			
			EXIT1_IR: 
				if(tms)
					state <= UPDATE_IR;
				else
					state <= PAUSE_IR;
					
			PAUSE_IR: 
				if(tms)
					state <= EXIT2_IR;
				else
					state <= PAUSE_IR;
			
			EXIT2_IR: 
				if(tms)
					state <= UPDATE_IR;
				else
					state <= SHIFT_IR;
					
					
			SHIFT_DR:
				if(tms)
					state <= EXIT1_DR;
				else 
					state <= SHIFT_DR;
					
			UPDATE_DR:
				if(tms)
					state <= TEST_LOGIC_RESET;
				else
					state <= RUN_TEST_IDLE;
					
			SELECT_DR_SCAN: 
				if(tms)
					state <= SELECT_IR_SCAN;
				else
					state <= CAPTURE_DR;
					
			CAPTURE_DR: 
				if(tms)
					state <= EXIT1_DR;
				else
					state <= SHIFT_DR;
					
			EXIT1_DR: 
				if(tms)
					state <= UPDATE_DR;
				else
					state <= PAUSE_DR;
					
			PAUSE_DR: 
				if(tms)
					state <= EXIT2_DR;
				else
					state <= PAUSE_DR;
					
			EXIT2_DR: 
				if(tms)
					state <= UPDATE_DR;
				else
					state <= SHIFT_DR;
					
			default:
				state <= TEST_LOGIC_RESET;
		endcase
	end
end

always @(posedge tck) begin
	
	if(state == CAPTURE_IR)
		ir_shift = 4'b0001;
end

always @(posedge tck) begin

	if(state == SHIFT_IR)
		ir_shift <= {tdi, ir_shift[3:1]};
	
end

always @(posedge tck) begin
	
	if(state == UPDATE_IR) begin
		ir <= ir_shift;
		
		if (ir_shift == IDCODE)
			dr_shift <= idcode;
	end
		
end

always @(posedge tck) begin
	if( state == CAPTURE_DR) begin
		case(ir)
			IDCODE:
				dr_shift <= idcode;
			
			BYPASS:
				bypass_bit <= 1'b0;
		endcase
	end
end

always @(posedge tck) begin

	if( state == SHIFT_DR) begin
		case (ir)
			
			IDCODE:
			begin 
				dr_shift <= {tdi, dr_shift[31:1]};
				
			end
			
			BYPASS:
			begin
				tdo <= bypass_bit;
				bypass_bit <= tdi;
			end
			
		endcase
	end
end



always @(*) begin
	case(ir) 
		IDCODE:
			tdo = dr_shift[0];
			
		BYPASS:
			tdo = bypass_bit;
			
		default:
			tdo = 0;
		
	endcase
end

endmodule

Task-1/tb_jtag_tap.v
module tb_jtag;

reg tck;
reg tms;
reg tdi;
reg trst;

wire tdo;

reg [31:0] read_idcode;

integer i; 

jtag_tap dut(
	.tck(tck),
	.tms(tms),
	.tdi(tdi),
	.trst(trst),
	.tdo(tdo)
);

always #5 tck = ~tck;

task jtag_clk;  // perform ONE JTAG clock operation
begin
	@(posedge tck);
	#1;             // signals samples too early
end 
endtask

// What operations we want done by SHIFT_IR

task shift_ir;  
input [3:0] instruction; //4 bit instruction 
integer i;


begin
	tms = 0; jtag_clk(); //run-test idle
	tms = 1; jtag_clk(); //Select DR scan
	tms = 1; jtag_clk(); //Select IR scan
	tms = 0; jtag_clk(); //Capture IR
	tms = 0; jtag_clk(); //Shift Ir
	
	
	for( i = 0; i < 4; i = i + 1) begin   //JTAG is serial send bit one by one
		
		tdi = instruction[i];
		
		if(i == 3)       //after final bit change state
			tms = 1;     // moves to update_ir
		else
			tms = 0;
			
		jtag_clk();
	end

	
	tms = 1; //update ir
	jtag_clk();
	
	tms = 0; //run test idle
	jtag_clk();
end 
endtask


task shift_dr;  //instructions loaded now data reading
integer i;

begin

	tms = 0; jtag_clk(); //run-test idle
	tms = 1; jtag_clk(); //select dr scan
	tms = 0; jtag_clk(); //capture dr
	tms = 0; jtag_clk(); //shift dr
	
	read_idcode = 32'h00000000;
	
	for(i = 0; i < 32; i = i + 1) begin
		
		read_idcode[i] = tdo;
		$display("Bit %d : TDO = %b", i, tdo);
		
		if( i == 31)
			tms = 1;
		else 
			tms = 0;
		
		tdi=0;
		jtag_clk();
		
	end
	
	tms = 1; jtag_clk(); //update dr
	tms = 0; jtag_clk();
	
end
endtask

initial begin 

	$dumpfile("jtag_tap.vcd");
	$dumpvars(0, tb_jtag);
	
	tck = 0;
	tms = 1;
	tdi = 0;
	trst = 1;
	
	read_idcode = 32'h0;
	
	#20;
	trst = 0;
	
	$display(" Shift IDCODE Ins");
	
	shift_ir(4'b0001);
	
	$display(" Read Data Message ");
	
	shift_dr();
	
	$display("Read IDCODE = %h", read_idcode);
	
	if(read_idcode == 32'h81262776) $display("pass");
	
	else $display("fail");
	
	#50;
	$finish;

end
endmodule

Task-1/jtag_tap.vcd
$date
	Tue May 26 00:22:41 2026
$end
$version
	Icarus Verilog
$end
$timescale
	1s
$end
$scope module tb_jtag $end
$var wire 1 ! tdo $end
$var reg 32 " read_idcode [31:0] $end
$var reg 1 # tck $end
$var reg 1 $ tdi $end
$var reg 1 % tms $end
$var reg 1 & trst $end
$scope module dut $end
$var wire 1 # tck $end
$var wire 1 $ tdi $end
$var wire 1 % tms $end
$var wire 1 & trst $end
$var reg 1 ' bypass_bit $end
$var reg 32 ( dr_shift [31:0] $end
$var reg 32 ) idcode [31:0] $end
$var reg 4 * ir [3:0] $end
$var reg 4 + ir_shift [3:0] $end
$var reg 4 , state [3:0] $end
$var reg 1 ! tdo $end
$upscope $end
$scope task jtag_clk $end
$upscope $end
$scope task shift_dr $end
$var integer 32 - i [31:0] $end
$upscope $end
$scope task shift_ir $end
$var reg 4 . instruction [3:0] $end
$var integer 32 / i [31:0] $end
$upscope $end
$upscope $end
$enddefinitions $end
#0
$dumpvars
bx /
bx .
bx -
b0 ,
b0 +
b0 *
b10000001001001100010011101110110 )
b0 (
0'
1&
1%
0$
0#
b0 "
0!
$end
#5
1#
#10
0#
#15
1#
#20
0#
0%
b1 .
0&
#25
b1 ,
1#
#26
1%
#30
0#
#35
b1011 ,
1#
#40
0#
#45
b100 ,
1#
#46
0%
#50
0#
#55
b101 ,
1#
#60
0#
#65
b10 ,
b1 +
1#
#66
1$
b0 /
#70
0#
#75
b1000 +
1#
#76
0$
b1 /
#80
0#
#85
b100 +
1#
#86
b10 /
#90
0#
#95
b10 +
1#
#96
1%
b11 /
#100
0#
#105
b1 +
b110 ,
1#
#106
b100 /
#110
0#
#115
b11 ,
1#
#116
0%
#120
0#
#125
b10000001001001100010011101110110 (
b1 *
b1 ,
1#
#130
0#
#135
1#
#136
1%
#140
0#
#145
b1011 ,
1#
#146
0%
#150
0#
#155
b1100 ,
1#
#160
0#
#165
b1001 ,
1#
#166
b0 -
#170
0#
#175
1!
b1000000100100110001001110111011 (
1#
#176
b10 "
b1 -
#180
0#
#185
b100000010010011000100111011101 (
1#
#186
b110 "
b10 -
#190
0#
#195
0!
b10000001001001100010011101110 (
1#
#196
b11 -
#200
0#
#205
1!
b1000000100100110001001110111 (
1#
#206
b10110 "
b100 -
#210
0#
#215
b100000010010011000100111011 (
1#
#216
b110110 "
b101 -
#220
0#
#225
b10000001001001100010011101 (
1#
#226
b1110110 "
b110 -
#230
0#
#235
0!
b1000000100100110001001110 (
1#
#236
b111 -
#240
0#
#245
1!
b100000010010011000100111 (
1#
#246
b101110110 "
b1000 -
#250
0#
#255
b10000001001001100010011 (
1#
#256
b1101110110 "
b1001 -
#260
0#
#265
b1000000100100110001001 (
1#
#266
b11101110110 "
b1010 -
#270
0#
#275
0!
b100000010010011000100 (
1#
#276
b1011 -
#280
0#
#285
b10000001001001100010 (
1#
#286
b1100 -
#290
0#
#295
1!
b1000000100100110001 (
1#
#296
b10011101110110 "
b1101 -
#300
0#
#305
0!
b100000010010011000 (
1#
#306
b1110 -
#310
0#
#315
b10000001001001100 (
1#
#316
b1111 -
#320
0#
#325
b1000000100100110 (
1#
#326
b10000 -
#330
0#
#335
1!
b100000010010011 (
1#
#336
b100010011101110110 "
b10001 -
#340
0#
#345
b10000001001001 (
1#
#346
b1100010011101110110 "
b10010 -
#350
0#
#355
0!
b1000000100100 (
1#
#356
b10011 -
#360
0#
#365
b100000010010 (
1#
#366
b10100 -
#370
0#
#375
1!
b10000001001 (
1#
#376
b1001100010011101110110 "
b10101 -
#380
0#
#385
0!
b1000000100 (
1#
#386
b10110 -
#390
0#
#395
b100000010 (
1#
#396
b10111 -
#400
0#
#405
1!
b10000001 (
1#
#406
b1001001100010011101110110 "
b11000 -
#410
0#
#415
0!
b1000000 (
1#
#416
b11001 -
#420
0#
#425
b100000 (
1#
#426
b11010 -
#430
0#
#435
b10000 (
1#
#436
b11011 -
#440
0#
#445
b1000 (
1#
#446
b11100 -
#450
0#
#455
b100 (
1#
#456
b11101 -
#460
0#
#465
b10 (
1#
#466
b11110 -
#470
0#
#475
1!
b1 (
1#
#476
1%
b10000001001001100010011101110110 "
b11111 -
#480
0#
#485
0!
b0 (
b1101 ,
1#
#486
b100000 -
#490
0#
#495
b1010 ,
1#
#496
0%
#500
0#
#505
b1 ,
1#
#510
0#
#515
1#
#520
0#
#525
1#
#530
0#
#535
1#
#540
0#
#545
1#
#550
0#
#555
1#
