Task-2/src/jtag_tap.v
//Tap is finite state machine
module jtag_tap(  
	input tck, //JTAG test clock
	input tms, //test mode select from tap state
	input tdi, // test data in serial input for ins and data 
	input trst, // active reset
	
	output tdo, //data data out seriol out for shifted ins/data
	
	output reg debug_halt_req, //req to halt processor
	output reg debug_resume_req, // request to resume processor
	output reg debug_reset_req, //request to reset the processor
	
	input debug_halted, // indicator that processor is halted
	input [31:0] debug_pc // processor current 32bit program counter value
);

reg tdo_reg;

assign tdo = tdo_reg;

parameter TEST_LOGIC_RESET = 4'h0; //reset state
parameter RUN_TEST_IDLE = 4'h1; // idle state nothing happens

parameter SHIFT_IR = 4'h2; //shift instruction bits into/out of IR
parameter UPDATE_IR = 4'h3;
parameter SELECT_IR_SCAN = 4'h4; 
parameter CAPTURE_IR = 4'h5;
parameter EXIT1_IR = 4'h6;
parameter PAUSE_IR = 4'h7;
parameter EXIT2_IR = 4'h8;

parameter SHIFT_DR = 4'h9;
parameter UPDATE_DR = 4'hA;
parameter SELECT_DR_SCAN = 4'hB; 
parameter CAPTURE_DR = 4'hC;
parameter EXIT1_DR = 4'hD;
parameter PAUSE_DR = 4'hE;
parameter EXIT2_DR = 4'hF;

reg[3:0] state;


// JTAG INSTRUCTIONS
parameter IDCODE = 4'b0001; //read device identification code
parameter DEBUG_CTRL = 4'b0010; // Access a debug control register
parameter DEBUG_STATUS = 4'b0011; // Acess status debug status register
parameter DEBUG_PC = 4'b0100; //Read or write processor program counter
parameter BYPASS = 4'b1111; // select the 1 bit bypass register to min scan chain length


reg[3:0] ir;
reg[3:0] ir_shift;

reg[31:0] idcode;
reg[31:0] dr_shift;
reg bypass_bit;


initial begin 
	state = TEST_LOGIC_RESET;
	ir = 4'b0000;
	ir_shift = 4'b0000;
	idcode = 32'h81262776;
	dr_shift = 32'h00000000;
	bypass_bit = 1'b0;
	tdo_reg = 1'b0;
	
end

always @(posedge tck or posedge trst) begin
	
	if(trst)
		state <= TEST_LOGIC_RESET;
		
	else begin
		case (state)
		// TMS CONTROLS NAVIGATION
			TEST_LOGIC_RESET:
				if(tms)    
					state <= TEST_LOGIC_RESET;
				else 
					state <= RUN_TEST_IDLE;
			
			RUN_TEST_IDLE:
				if(tms) 
					state <= SELECT_DR_SCAN;
				else 
					state <= RUN_TEST_IDLE;
			
			SELECT_DR_SCAN: 
				if(tms)
					state <= SELECT_IR_SCAN;
				else
					state <= CAPTURE_DR;		
								
			CAPTURE_DR: 
				if(tms)
					state <= EXIT1_DR;
				else
					state <= SHIFT_DR;
					
			SHIFT_DR:
				if(tms)
					state <= EXIT1_DR;
				else 
					state <= SHIFT_DR;
					
			EXIT1_DR: 
				if(tms)
					state <= UPDATE_DR;
				else
					state <= PAUSE_DR;
					
			PAUSE_DR: 
				if(tms)
					state <= EXIT2_DR;
				else
					state <= PAUSE_DR;
					
			EXIT2_DR: 
				if(tms)
					state <= UPDATE_DR;
				else
					state <= SHIFT_DR;
							
			UPDATE_DR:
				if(tms)
					state <= SELECT_DR_SCAN;
				else
					state <= RUN_TEST_IDLE;
					
			
			SELECT_IR_SCAN:
				if(tms) 
					state <= TEST_LOGIC_RESET;
				else
					state <= CAPTURE_IR;
					
			CAPTURE_IR: 
				if(tms)
					state <= EXIT1_IR;
				else
					state <= SHIFT_IR;
			
			SHIFT_IR:
				if(tms)
					state <= EXIT1_IR;
				else
					state <= SHIFT_IR;
					
			EXIT1_IR: 
				if(tms)
					state <= UPDATE_IR;
				else
					state <= PAUSE_IR;
					
			PAUSE_IR: 
				if(tms)
					state <= EXIT2_IR;
				else
					state <= PAUSE_IR;
			
			EXIT2_IR: 
				if(tms)
					state <= UPDATE_IR;
				else
					state <= SHIFT_IR;
					
			
			UPDATE_IR:
				if(tms)
					state <= SELECT_DR_SCAN;
				else 
					state <= RUN_TEST_IDLE;

					
			default:
				state <= TEST_LOGIC_RESET;
		endcase
	end
end

always @(posedge tck) begin
	
	if(state == CAPTURE_IR)
		ir_shift = 4'b0001;
end

always @(posedge tck) begin

	if(state == SHIFT_IR)
		ir_shift <= {tdi, ir_shift[3:1]};
	
end

always @(posedge tck) begin
	
	if(state == UPDATE_IR) begin
		ir <= ir_shift;
		
		if (ir_shift == IDCODE)
			dr_shift <= idcode;
	end
		
end

always @(posedge tck) begin
	if( state == CAPTURE_DR) begin
		case(ir)
			IDCODE:
				dr_shift <= idcode;
			
			DEBUG_STATUS:
    				dr_shift <= {31'b0, debug_halted};
    				
    			DEBUG_PC:
    				dr_shift <= debug_pc;
    
			BYPASS:
				bypass_bit <= 1'b0;
		endcase
	end
end

always @(posedge tck) begin
	debug_halt_req <=0;
	debug_resume_req <=0;
	debug_reset_req <=0;
	
	if(state == UPDATE_DR && ir == DEBUG_CTRL) begin
		debug_halt_req <= dr_shift[0];
		debug_resume_req <= dr_shift[1];
		debug_reset_req <= dr_shift[2];
	end	
end

always @(posedge tck) begin

	if( state == SHIFT_DR) begin
		case (ir)
			
			IDCODE,
			DEBUG_STATUS,
			DEBUG_PC,
			DEBUG_CTRL:
			begin 
				tdo_reg <= dr_shift[0];
				dr_shift <= {tdi, dr_shift[31:1]};
				
			end
			
			BYPASS:
			begin
				tdo_reg <= bypass_bit;
				bypass_bit <= tdi;
			end
			
		endcase
	end
end

endmodule

Task-2/src/tb_jtag_tap.v
module tb_jtag;

reg tck;
reg tms;
reg tdi;
reg trst;

wire tdo;

wire debug_halt_req;
wire debug_resume_req;
wire debug_reset_req;

reg debug_halted;
reg [31:0] debug_pc;

reg [31:0] dr_data;

integer i; 

jtag_tap dut(
	.tck(tck),
	.tms(tms),
	.tdi(tdi),
	.trst(trst),
	
	.tdo(tdo),
	
	.debug_halt_req(debug_halt_req),
	.debug_resume_req(debug_resume_req),
	.debug_reset_req(debug_reset_req),
	
	.debug_halted(debug_halted),
	.debug_pc(debug_pc)
);

always #5 tck = ~tck;

task jtag_clk;  // perform ONE JTAG clock operation
begin
	@(posedge tck);
	#1;             // signals samples too early
end 
endtask

task tap_reset;
integer k;
begin

	tms = 1;
	for(k = 0; k < 6; k = k + 1) jtag_clk();
	
	tms = 1;
	jtag_clk();
	
end 
endtask

// What operations we want done by SHIFT_IR

task shift_ir;  
input [3:0] instruction; //4 bit instruction 
integer i;


begin
	tms = 0; jtag_clk(); //run-test idle
	tms = 1; jtag_clk(); //Select DR scan
	tms = 1; jtag_clk(); //Select IR scan
	tms = 0; jtag_clk(); //Capture IR
	tms = 0; jtag_clk(); //Shift Ir
	
	
	for( i = 0; i < 4; i = i + 1) begin   //JTAG is serial send bit one by one
		
		tdi = instruction[i];
		
		if(i == 3)       //after final bit change state
			tms = 1;     // moves to update_ir
		else
			tms = 0;
			
		jtag_clk();
	end

	
	tms = 1; //update ir
	jtag_clk();
	
	tms = 0; //run test idle
	jtag_clk();
end 
endtask


task shift_dr_read32;  //instructions loaded now data reading
output [31:0] data;
integer i;

begin
	
	tms = 0; jtag_clk(); //run-test idle
	tms = 1; jtag_clk(); //select dr scan
	tms = 0; jtag_clk(); //capture dr
	tms = 0; jtag_clk(); //shift dr
	
	data = 32'h00000000;
	
	for(i = 0; i < 32; i = i + 1) begin
		
		if( i == 31)
			tms = 1;
		else 
			tms = 0;
		
		tdi=0;
		jtag_clk();
		
		data[i] = tdo;
		$display("Bit %d : TDO = %b", i, tdo);
	end
	
	tms = 1; jtag_clk(); //update dr
	tms = 0; jtag_clk();
	
end
endtask

task shift_dr_write32;
input [31:0] data;
integer i;

begin 
	tms = 1; jtag_clk(); // Select DR Scan
	tms = 0; jtag_clk(); // capture_dr
	tms = 0; jtag_clk(); // shift_dr
	
	for(i = 0; i < 32; i = i+1) begin
		tdi = data[i];
		
		if( i == 31) tms = 1;
		else tms = 0;
		
		jtag_clk();
	end
	
	tms = 1; jtag_clk(); //update_dr
	tms = 0; jtag_clk(); //run test idle
	
end
endtask

initial begin 

	$dumpfile("jtag_tap.vcd");
	$dumpvars(0, tb_jtag);
	
	tck = 0;
	tms = 1;
	tdi = 0;
	trst = 1;
	
	debug_halted = 1;
	debug_pc = 32'h80000000;
	
	dr_data = 32'h0;
	
	#20;
	trst = 0;
	// IDCODE TEST
	
	$display(" IDCODE TEST");
	
	shift_ir(4'b0001);
	shift_dr_read32(dr_data);
	
	
	$display("Read IDCODE = %h", dr_data);
	
	if(dr_data == 32'h81262776) $display("IDCODE PASS\n");
	
	else $display("IDCODE FAIL");
	
	
	//DEBUG STATUS
	
	$display (" DEBUG STATUS");
	shift_ir (4'b0011);
	shift_dr_read32(dr_data);
	
	$display("DEBUG_STATUS = %h", dr_data);
	
	if(dr_data == 32'h00000001) $display("Debug status pass\n");
	else $display("Debug status fail");
	
	//Debug PC
	
	$display("Debug PC");
	shift_ir(4'b0100);
	shift_dr_read32(dr_data);
	
	$display("Debug PC = %h", dr_data);
	
	if(dr_data == 32'h80000000) $display ("Debug pc pass \n");
	else $display(" Debug pc fail ");
	
	
	//Debug Ctrl Halt
	
	$display("Debug control halt test");
	
	shift_ir(4'b0010);
	shift_dr_write32(32'h00000001);
	
	#20;

		
	// Debug Control Resume
	$display("Debug Control Resume test");
	
	shift_ir(4'b0010);
	shift_dr_write32(32'h00000002);
	
	#20;

	//Debug Control Reset
	
	$display("Debug Control Reset test");
	
	shift_ir(4'b0010);
	shift_dr_write32(32'h00000004);
	
		
	#100;
	$finish;

end

always @(posedge tck) begin

    if(debug_halt_req)
        $display("HALT requested generated\n");

    if(debug_resume_req)
        $display("RESUME requested generated\n");

    if(debug_reset_req)
        $display("RESET requested generated\n");

end
endmodule

Task-2/src/jtag_tap.vcd
$date
	Wed Jun  3 23:48:16 2026
$end
$version
	Icarus Verilog
$end
$timescale
	1s
$end
$scope module tb_jtag $end
$var wire 1 ! tdo $end
$var wire 1 " debug_resume_req $end
$var wire 1 # debug_reset_req $end
$var wire 1 $ debug_halt_req $end
$var reg 1 % debug_halted $end
$var reg 32 & debug_pc [31:0] $end
$var reg 32 ' dr_data [31:0] $end
$var reg 1 ( tck $end
$var reg 1 ) tdi $end
$var reg 1 * tms $end
$var reg 1 + trst $end
$scope module dut $end
$var wire 1 % debug_halted $end
$var wire 32 , debug_pc [31:0] $end
$var wire 1 ( tck $end
$var wire 1 ) tdi $end
$var wire 1 ! tdo $end
$var wire 1 * tms $end
$var wire 1 + trst $end
$var reg 1 - bypass_bit $end
$var reg 1 $ debug_halt_req $end
$var reg 1 # debug_reset_req $end
$var reg 1 " debug_resume_req $end
$var reg 32 . dr_shift [31:0] $end
$var reg 32 / idcode [31:0] $end
$var reg 4 0 ir [3:0] $end
$var reg 4 1 ir_shift [3:0] $end
$var reg 4 2 state [3:0] $end
$var reg 1 3 tdo_reg $end
$upscope $end
$scope task jtag_clk $end
$upscope $end
$scope task shift_dr_read32 $end
$var reg 32 4 data [31:0] $end
$var integer 32 5 i [31:0] $end
$upscope $end
$scope task shift_dr_write32 $end
$var reg 32 6 data [31:0] $end
$var integer 32 7 i [31:0] $end
$upscope $end
$scope task shift_ir $end
$var reg 4 8 instruction [3:0] $end
$var integer 32 9 i [31:0] $end
$upscope $end
$scope task tap_reset $end
$var integer 32 : k [31:0] $end
$upscope $end
$upscope $end
$enddefinitions $end
#0
$dumpvars
bx :
bx 9
bx 8
bx 7
bx 6
bx 5
bx 4
03
b0 2
b0 1
b0 0
b10000001001001100010011101110110 /
b0 .
0-
b10000000000000000000000000000000 ,
1+
1*
0)
0(
b0 '
b10000000000000000000000000000000 &
1%
x$
x#
x"
0!
$end
#5
0#
0"
0$
1(
#10
0(
#15
1(
#20
0(
0*
b1 8
0+
#25
b1 2
1(
#26
1*
#30
0(
#35
b1011 2
1(
#40
0(
#45
b100 2
1(
#46
0*
#50
0(
#55
b101 2
1(
#60
0(
#65
b10 2
b1 1
1(
#66
1)
b0 9
#70
0(
#75
b1000 1
1(
#76
0)
b1 9
#80
0(
#85
b100 1
1(
#86
b10 9
#90
0(
#95
b10 1
1(
#96
1*
b11 9
#100
0(
#105
b1 1
b110 2
1(
#106
b100 9
#110
0(
#115
b11 2
1(
#116
0*
#120
0(
#125
b10000001001001100010011101110110 .
b1 0
b1 2
1(
#130
0(
#135
1(
#136
1*
#140
0(
#145
b1011 2
1(
#146
0*
#150
0(
#155
b1100 2
1(
#160
0(
#165
b1001 2
1(
#166
b0 5
b0 4
#170
0(
#175
b1000000100100110001001110111011 .
1(
#176
b1 5
#180
0(
#185
b100000010010011000100111011101 .
1!
13
1(
#186
b10 5
b10 4
#190
0(
#195
b10000001001001100010011101110 .
1(
#196
b11 5
b110 4
#200
0(
#205
b1000000100100110001001110111 .
0!
03
1(
#206
b100 5
#210
0(
#215
b100000010010011000100111011 .
1!
13
1(
#216
b101 5
b10110 4
#220
0(
#225
b10000001001001100010011101 .
1(
#226
b110 5
b110110 4
#230
0(
#235
b1000000100100110001001110 .
1(
#236
b111 5
b1110110 4
#240
0(
#245
b100000010010011000100111 .
0!
03
1(
#246
b1000 5
#250
0(
#255
b10000001001001100010011 .
1!
13
1(
#256
b1001 5
b101110110 4
#260
0(
#265
b1000000100100110001001 .
1(
#266
b1010 5
b1101110110 4
#270
0(
#275
b100000010010011000100 .
1(
#276
b1011 5
b11101110110 4
#280
0(
#285
b10000001001001100010 .
0!
03
1(
#286
b1100 5
#290
0(
#295
b1000000100100110001 .
1(
#296
b1101 5
#300
0(
#305
b100000010010011000 .
1!
13
1(
#306
b1110 5
b10011101110110 4
#310
0(
#315
b10000001001001100 .
0!
03
1(
#316
b1111 5
#320
0(
#325
b1000000100100110 .
1(
#326
b10000 5
#330
0(
#335
b100000010010011 .
1(
#336
b10001 5
#340
0(
#345
b10000001001001 .
1!
13
1(
#346
b10010 5
b100010011101110110 4
#350
0(
#355
b1000000100100 .
1(
#356
b10011 5
b1100010011101110110 4
#360
0(
#365
b100000010010 .
0!
03
1(
#366
b10100 5
#370
0(
#375
b10000001001 .
1(
#376
b10101 5
#380
0(
#385
b1000000100 .
1!
13
1(
#386
b10110 5
b1001100010011101110110 4
#390
0(
#395
b100000010 .
0!
03
1(
#396
b10111 5
#400
0(
#405
b10000001 .
1(
#406
b11000 5
#410
0(
#415
b1000000 .
1!
13
1(
#416
b11001 5
b1001001100010011101110110 4
#420
0(
#425
b100000 .
0!
03
1(
#426
b11010 5
#430
0(
#435
b10000 .
1(
#436
b11011 5
#440
0(
#445
b1000 .
1(
#446
b11100 5
#450
0(
#455
b100 .
1(
#456
b11101 5
#460
0(
#465
b10 .
1(
#466
b11110 5
#470
0(
#475
b1 .
1(
#476
1*
b11111 5
#480
0(
#485
b0 .
1!
13
b1101 2
1(
#486
b100000 5
b10000001001001100010011101110110 4
#490
0(
#495
b1010 2
1(
#496
0*
#500
0(
#505
b1 2
1(
#506
b11 8
b10000001001001100010011101110110 '
#510
0(
#515
1(
#516
1*
#520
0(
#525
b1011 2
1(
#530
0(
#535
b100 2
1(
#536
0*
#540
0(
#545
b101 2
1(
#550
0(
#555
b10 2
1(
#556
1)
b0 9
#560
0(
#565
b1000 1
1(
#566
b1 9
#570
0(
#575
b1100 1
1(
#576
0)
b10 9
#580
0(
#585
b110 1
1(
#586
1*
b11 9
#590
0(
#595
b11 1
b110 2
1(
#596
b100 9
#600
0(
#605
b11 2
1(
#606
0*
#610
0(
#615
b11 0
b1 2
1(
#620
0(
#625
1(
#626
1*
#630
0(
#635
b1011 2
1(
#636
0*
#640
0(
#645
b1100 2
1(
#650
0(
#655
b1 .
b1001 2
1(
#656
b0 5
b0 4
#660
0(
#665
b0 .
1(
#666
b1 5
b1 4
#670
0(
#675
0!
03
1(
#676
b10 5
#680
0(
#685
1(
#686
b11 5
#690
0(
#695
1(
#696
b100 5
#700
0(
#705
1(
#706
b101 5
#710
0(
#715
1(
#716
b110 5
#720
0(
#725
1(
#726
b111 5
#730
0(
#735
1(
#736
b1000 5
#740
0(
#745
1(
#746
b1001 5
#750
0(
#755
1(
#756
b1010 5
#760
0(
#765
1(
#766
b1011 5
#770
0(
#775
1(
#776
b1100 5
#780
0(
#785
1(
#786
b1101 5
#790
0(
#795
1(
#796
b1110 5
#800
0(
#805
1(
#806
b1111 5
#810
0(
#815
1(
#816
b10000 5
#820
0(
#825
1(
#826
b10001 5
#830
0(
#835
1(
#836
b10010 5
#840
0(
#845
1(
#846
b10011 5
#850
0(
#855
1(
#856
b10100 5
#860
0(
#865
1(
#866
b10101 5
#870
0(
#875
1(
#876
b10110 5
#880
0(
#885
1(
#886
b10111 5
#890
0(
#895
1(
#896
b11000 5
#900
0(
#905
1(
#906
b11001 5
#910
0(
#915
1(
#916
b11010 5
#920
0(
#925
1(
#926
b11011 5
#930
0(
#935
1(
#936
b11100 5
#940
0(
#945
1(
#946
b11101 5
#950
0(
#955
1(
#956
b11110 5
#960
0(
#965
1(
#966
1*
b11111 5
#970
0(
#975
b1101 2
1(
#976
b100000 5
#980
0(
#985
b1010 2
1(
#986
0*
#990
0(
#995
b1 2
1(
#996
b100 8
b1 '
#1000
0(
#1005
1(
#1006
1*
#1010
0(
#1015
b1011 2
1(
#1020
0(
#1025
b100 2
1(
#1026
0*
#1030
0(
#1035
b101 2
1(
#1040
0(
#1045
b10 2
b1 1
1(
#1046
b0 9
#1050
0(
#1055
b0 1
1(
#1056
b1 9
#1060
0(
#1065
1(
#1066
1)
b10 9
#1070
0(
#1075
b1000 1
1(
#1076
1*
0)
b11 9
#1080
0(
#1085
b100 1
b110 2
1(
#1086
b100 9
#1090
0(
#1095
b11 2
1(
#1096
0*
#1100
0(
#1105
b100 0
b1 2
1(
#1110
0(
#1115
1(
#1116
1*
#1120
0(
#1125
b1011 2
1(
#1126
0*
#1130
0(
#1135
b1100 2
1(
#1140
0(
#1145
b10000000000000000000000000000000 .
b1001 2
1(
#1146
b0 5
b0 4
#1150
0(
#1155
b1000000000000000000000000000000 .
1(
#1156
b1 5
#1160
0(
#1165
b100000000000000000000000000000 .
1(
#1166
b10 5
#1170
0(
#1175
b10000000000000000000000000000 .
1(
#1176
b11 5
#1180
0(
#1185
b1000000000000000000000000000 .
1(
#1186
b100 5
#1190
0(
#1195
b100000000000000000000000000 .
1(
#1196
b101 5
#1200
0(
#1205
b10000000000000000000000000 .
1(
#1206
b110 5
#1210
0(
#1215
b1000000000000000000000000 .
1(
#1216
b111 5
#1220
0(
#1225
b100000000000000000000000 .
1(
#1226
b1000 5
#1230
0(
#1235
b10000000000000000000000 .
1(
#1236
b1001 5
#1240
0(
#1245
b1000000000000000000000 .
1(
#1246
b1010 5
#1250
0(
#1255
b100000000000000000000 .
1(
#1256
b1011 5
#1260
0(
#1265
b10000000000000000000 .
1(
#1266
b1100 5
#1270
0(
#1275
b1000000000000000000 .
1(
#1276
b1101 5
#1280
0(
#1285
b100000000000000000 .
1(
#1286
b1110 5
#1290
0(
#1295
b10000000000000000 .
1(
#1296
b1111 5
#1300
0(
#1305
b1000000000000000 .
1(
#1306
b10000 5
#1310
0(
#1315
b100000000000000 .
1(
#1316
b10001 5
#1320
0(
#1325
b10000000000000 .
1(
#1326
b10010 5
#1330
0(
#1335
b1000000000000 .
1(
#1336
b10011 5
#1340
0(
#1345
b100000000000 .
1(
#1346
b10100 5
#1350
0(
#1355
b10000000000 .
1(
#1356
b10101 5
#1360
0(
#1365
b1000000000 .
1(
#1366
b10110 5
#1370
0(
#1375
b100000000 .
1(
#1376
b10111 5
#1380
0(
#1385
b10000000 .
1(
#1386
b11000 5
#1390
0(
#1395
b1000000 .
1(
#1396
b11001 5
#1400
0(
#1405
b100000 .
1(
#1406
b11010 5
#1410
0(
#1415
b10000 .
1(
#1416
b11011 5
#1420
0(
#1425
b1000 .
1(
#1426
b11100 5
#1430
0(
#1435
b100 .
1(
#1436
b11101 5
#1440
0(
#1445
b10 .
1(
#1446
b11110 5
#1450
0(
#1455
b1 .
1(
#1456
1*
b11111 5
#1460
0(
#1465
b0 .
1!
13
b1101 2
1(
#1466
b100000 5
b10000000000000000000000000000000 4
#1470
0(
#1475
b1010 2
1(
#1476
0*
#1480
0(
#1485
b1 2
1(
#1486
b10 8
b10000000000000000000000000000000 '
#1490
0(
#1495
1(
#1496
1*
#1500
0(
#1505
b1011 2
1(
#1510
0(
#1515
b100 2
1(
#1516
0*
#1520
0(
#1525
b101 2
1(
#1530
0(
#1535
b10 2
b1 1
1(
#1536
b0 9
#1540
0(
#1545
b0 1
1(
#1546
1)
b1 9
#1550
0(
#1555
b1000 1
1(
#1556
0)
b10 9
#1560
0(
#1565
b100 1
1(
#1566
1*
b11 9
#1570
0(
#1575
b10 1
b110 2
1(
#1576
b100 9
#1580
0(
#1585
b11 2
1(
#1586
0*
#1590
0(
#1595
b10 0
b1 2
1(
#1596
1*
b1 6
#1600
0(
#1605
b1011 2
1(
#1606
0*
#1610
0(
#1615
b1100 2
1(
#1620
0(
#1625
b1001 2
1(
#1626
1)
b0 7
#1630
0(
#1635
b10000000000000000000000000000000 .
0!
03
1(
#1636
0)
b1 7
#1640
0(
#1645
b1000000000000000000000000000000 .
1(
#1646
b10 7
#1650
0(
#1655
b100000000000000000000000000000 .
1(
#1656
b11 7
#1660
0(
#1665
b10000000000000000000000000000 .
1(
#1666
b100 7
#1670
0(
#1675
b1000000000000000000000000000 .
1(
#1676
b101 7
#1680
0(
#1685
b100000000000000000000000000 .
1(
#1686
b110 7
#1690
0(
#1695
b10000000000000000000000000 .
1(
#1696
b111 7
#1700
0(
#1705
b1000000000000000000000000 .
1(
#1706
b1000 7
#1710
0(
#1715
b100000000000000000000000 .
1(
#1716
b1001 7
#1720
0(
#1725
b10000000000000000000000 .
1(
#1726
b1010 7
#1730
0(
#1735
b1000000000000000000000 .
1(
#1736
b1011 7
#1740
0(
#1745
b100000000000000000000 .
1(
#1746
b1100 7
#1750
0(
#1755
b10000000000000000000 .
1(
#1756
b1101 7
#1760
0(
#1765
b1000000000000000000 .
1(
#1766
b1110 7
#1770
0(
#1775
b100000000000000000 .
1(
#1776
b1111 7
#1780
0(
#1785
b10000000000000000 .
1(
#1786
b10000 7
#1790
0(
#1795
b1000000000000000 .
1(
#1796
b10001 7
#1800
0(
#1805
b100000000000000 .
1(
#1806
b10010 7
#1810
0(
#1815
b10000000000000 .
1(
#1816
b10011 7
#1820
0(
#1825
b1000000000000 .
1(
#1826
b10100 7
#1830
0(
#1835
b100000000000 .
1(
#1836
b10101 7
#1840
0(
#1845
b10000000000 .
1(
#1846
b10110 7
#1850
0(
#1855
b1000000000 .
1(
#1856
b10111 7
#1860
0(
#1865
b100000000 .
1(
#1866
b11000 7
#1870
0(
#1875
b10000000 .
1(
#1876
b11001 7
#1880
0(
#1885
b1000000 .
1(
#1886
b11010 7
#1890
0(
#1895
b100000 .
1(
#1896
b11011 7
#1900
0(
#1905
b10000 .
1(
#1906
b11100 7
#1910
0(
#1915
b1000 .
1(
#1916
b11101 7
#1920
0(
#1925
b100 .
1(
#1926
b11110 7
#1930
0(
#1935
b10 .
1(
#1936
1*
b11111 7
#1940
0(
#1945
b1 .
b1101 2
1(
#1946
b100000 7
#1950
0(
#1955
b1010 2
1(
#1956
0*
#1960
0(
#1965
1$
b1 2
1(
#1970
0(
#1975
0$
1(
#1980
0(
#1985
1(
#1990
0(
#1995
1(
#1996
1*
#2000
0(
#2005
b1011 2
1(
#2010
0(
#2015
b100 2
1(
#2016
0*
#2020
0(
#2025
b101 2
1(
#2030
0(
#2035
b10 2
b1 1
1(
#2036
b0 9
#2040
0(
#2045
b0 1
1(
#2046
1)
b1 9
#2050
0(
#2055
b1000 1
1(
#2056
0)
b10 9
#2060
0(
#2065
b100 1
1(
#2066
1*
b11 9
#2070
0(
#2075
b10 1
b110 2
1(
#2076
b100 9
#2080
0(
#2085
b11 2
1(
#2086
0*
#2090
0(
#2095
b1 2
1(
#2096
1*
b10 6
#2100
0(
#2105
b1011 2
1(
#2106
0*
#2110
0(
#2115
b1100 2
1(
#2120
0(
#2125
b1001 2
1(
#2126
b0 7
#2130
0(
#2135
b0 .
1!
13
1(
#2136
1)
b1 7
#2140
0(
#2145
b10000000000000000000000000000000 .
0!
03
1(
#2146
0)
b10 7
#2150
0(
#2155
b1000000000000000000000000000000 .
1(
#2156
b11 7
#2160
0(
#2165
b100000000000000000000000000000 .
1(
#2166
b100 7
#2170
0(
#2175
b10000000000000000000000000000 .
1(
#2176
b101 7
#2180
0(
#2185
b1000000000000000000000000000 .
1(
#2186
b110 7
#2190
0(
#2195
b100000000000000000000000000 .
1(
#2196
b111 7
#2200
0(
#2205
b10000000000000000000000000 .
1(
#2206
b1000 7
#2210
0(
#2215
b1000000000000000000000000 .
1(
#2216
b1001 7
#2220
0(
#2225
b100000000000000000000000 .
1(
#2226
b1010 7
#2230
0(
#2235
b10000000000000000000000 .
1(
#2236
b1011 7
#2240
0(
#2245
b1000000000000000000000 .
1(
#2246
b1100 7
#2250
0(
#2255
b100000000000000000000 .
1(
#2256
b1101 7
#2260
0(
#2265
b10000000000000000000 .
1(
#2266
b1110 7
#2270
0(
#2275
b1000000000000000000 .
1(
#2276
b1111 7
#2280
0(
#2285
b100000000000000000 .
1(
#2286
b10000 7
#2290
0(
#2295
b10000000000000000 .
1(
#2296
b10001 7
#2300
0(
#2305
b1000000000000000 .
1(
#2306
b10010 7
#2310
0(
#2315
b100000000000000 .
1(
#2316
b10011 7
#2320
0(
#2325
b10000000000000 .
1(
#2326
b10100 7
#2330
0(
#2335
b1000000000000 .
1(
#2336
b10101 7
#2340
0(
#2345
b100000000000 .
1(
#2346
b10110 7
#2350
0(
#2355
b10000000000 .
1(
#2356
b10111 7
#2360
0(
#2365
b1000000000 .
1(
#2366
b11000 7
#2370
0(
#2375
b100000000 .
1(
#2376
b11001 7
#2380
0(
#2385
b10000000 .
1(
#2386
b11010 7
#2390
0(
#2395
b1000000 .
1(
#2396
b11011 7
#2400
0(
#2405
b100000 .
1(
#2406
b11100 7
#2410
0(
#2415
b10000 .
1(
#2416
b11101 7
#2420
0(
#2425
b1000 .
1(
#2426
b11110 7
#2430
0(
#2435
b100 .
1(
#2436
1*
b11111 7
#2440
0(
#2445
b10 .
b1101 2
1(
#2446
b100000 7
#2450
0(
#2455
b1010 2
1(
#2456
0*
#2460
0(
#2465
1"
b1 2
1(
#2470
0(
#2475
0"
1(
#2480
0(
#2485
1(
#2490
0(
#2495
1(
#2496
1*
#2500
0(
#2505
b1011 2
1(
#2510
0(
#2515
b100 2
1(
#2516
0*
#2520
0(
#2525
b101 2
1(
#2530
0(
#2535
b10 2
b1 1
1(
#2536
b0 9
#2540
0(
#2545
b0 1
1(
#2546
1)
b1 9
#2550
0(
#2555
b1000 1
1(
#2556
0)
b10 9
#2560
0(
#2565
b100 1
1(
#2566
1*
b11 9
#2570
0(
#2575
b10 1
b110 2
1(
#2576
b100 9
#2580
0(
#2585
b11 2
1(
#2586
0*
#2590
0(
#2595
b1 2
1(
#2596
1*
b100 6
#2600
0(
#2605
b1011 2
1(
#2606
0*
#2610
0(
#2615
b1100 2
1(
#2620
0(
#2625
b1001 2
1(
#2626
b0 7
#2630
0(
#2635
b1 .
1(
#2636
b1 7
#2640
0(
#2645
b0 .
1!
13
1(
#2646
1)
b10 7
#2650
0(
#2655
b10000000000000000000000000000000 .
0!
03
1(
#2656
0)
b11 7
#2660
0(
#2665
b1000000000000000000000000000000 .
1(
#2666
b100 7
#2670
0(
#2675
b100000000000000000000000000000 .
1(
#2676
b101 7
#2680
0(
#2685
b10000000000000000000000000000 .
1(
#2686
b110 7
#2690
0(
#2695
b1000000000000000000000000000 .
1(
#2696
b111 7
#2700
0(
#2705
b100000000000000000000000000 .
1(
#2706
b1000 7
#2710
0(
#2715
b10000000000000000000000000 .
1(
#2716
b1001 7
#2720
0(
#2725
b1000000000000000000000000 .
1(
#2726
b1010 7
#2730
0(
#2735
b100000000000000000000000 .
1(
#2736
b1011 7
#2740
0(
#2745
b10000000000000000000000 .
1(
#2746
b1100 7
#2750
0(
#2755
b1000000000000000000000 .
1(
#2756
b1101 7
#2760
0(
#2765
b100000000000000000000 .
1(
#2766
b1110 7
#2770
0(
#2775
b10000000000000000000 .
1(
#2776
b1111 7
#2780
0(
#2785
b1000000000000000000 .
1(
#2786
b10000 7
#2790
0(
#2795
b100000000000000000 .
1(
#2796
b10001 7
#2800
0(
#2805
b10000000000000000 .
1(
#2806
b10010 7
#2810
0(
#2815
b1000000000000000 .
1(
#2816
b10011 7
#2820
0(
#2825
b100000000000000 .
1(
#2826
b10100 7
#2830
0(
#2835
b10000000000000 .
1(
#2836
b10101 7
#2840
0(
#2845
b1000000000000 .
1(
#2846
b10110 7
#2850
0(
#2855
b100000000000 .
1(
#2856
b10111 7
#2860
0(
#2865
b10000000000 .
1(
#2866
b11000 7
#2870
0(
#2875
b1000000000 .
1(
#2876
b11001 7
#2880
0(
#2885
b100000000 .
1(
#2886
b11010 7
#2890
0(
#2895
b10000000 .
1(
#2896
b11011 7
#2900
0(
#2905
b1000000 .
1(
#2906
b11100 7
#2910
0(
#2915
b100000 .
1(
#2916
b11101 7
#2920
0(
#2925
b10000 .
1(
#2926
b11110 7
#2930
0(
#2935
b1000 .
1(
#2936
1*
b11111 7
#2940
0(
#2945
b100 .
b1101 2
1(
#2946
b100000 7
#2950
0(
#2955
b1010 2
1(
#2956
0*
#2960
0(
#2965
1#
b1 2
1(
#2970
0(
#2975
0#
1(
#2980
0(
#2985
1(
#2990
0(
#2995
1(
#3000
0(
#3005
1(
#3010
0(
#3015
1(
#3020
0(
#3025
1(
#3030
0(
#3035
1(
#3040
0(
#3045
1(
#3050
0(
#3055
1(
#3060
0(
#3065
1(
